djtools/__init__.py
djtools/__main__.py
djtools/version.py
djtools/collection/__init__.py
djtools/collection/collections.py
djtools/collection/config.py
djtools/collection/copy_playlists.py
djtools/collection/helpers.py
djtools/collection/playlist_builder.py
djtools/collection/playlists.py
djtools/collection/shuffle_playlists.py
djtools/collection/tracks.py
djtools/configs/__init__.py
djtools/configs/collection_playlists.yaml
djtools/configs/config.py
djtools/configs/config.yaml
djtools/configs/helpers.py
djtools/configs/logging.conf
djtools/configs/spotify_playlists.yaml
djtools/logs/empty.txt
djtools/spotify/__init__.py
djtools/spotify/config.py
djtools/spotify/helpers.py
djtools/spotify/playlist_builder.py
djtools/sync/__init__.py
djtools/sync/config.py
djtools/sync/helpers.py
djtools/sync/sync_operations.py
djtools/utils/__init__.py
djtools/utils/check_tracks.py
djtools/utils/config.py
djtools/utils/helpers.py
djtools/utils/url_download.py
dj_beatcloud-2.6.0.dist-info/LICENSE
dj_beatcloud-2.6.0.dist-info/METADATA
dj_beatcloud-2.6.0.dist-info/WHEEL
dj_beatcloud-2.6.0.dist-info/entry_points.txt
dj_beatcloud-2.6.0.dist-info/top_level.txt
dj_beatcloud-2.6.0.dist-info/RECORD
