Metadata-Version: 2.1
Name: dj-beatcloud
Version: 2.6.0
Summary: DJ Tools is a library for managing a collection of music.
Home-page: https://github.com/a-rich/DJ-tools
Author: Alex Richards
Author-email: alex.richards006@gmail.com
Keywords: DJ Rekordbox spotify reddit aws s3
Classifier: Development Status :: 4 - Beta
Classifier: Intended Audience :: Developers
Classifier: Intended Audience :: End Users/Desktop
Classifier: Intended Audience :: Other Audience
Classifier: License :: OSI Approved :: GNU General Public License v3 (GPLv3)
Classifier: Natural Language :: English
Classifier: Operating System :: MacOS :: MacOS X
Classifier: Operating System :: Microsoft :: Windows
Classifier: Operating System :: POSIX :: Linux
Classifier: Programming Language :: Python :: 3.6
Classifier: Programming Language :: Python :: 3.7
Classifier: Programming Language :: Python :: 3.8
Classifier: Programming Language :: Python :: 3.9
Classifier: Programming Language :: Python :: 3.10
Classifier: Programming Language :: Python :: 3.11
Classifier: Topic :: Multimedia :: Sound/Audio
Classifier: Topic :: Other/Nonlisted Topic
Requires-Python: >=3.6
License-File: LICENSE
Requires-Dist: asyncpraw (==7.6.1)
Requires-Dist: awscli (==1.27.45)
Requires-Dist: beautifulsoup4 (==4.11.1)
Requires-Dist: fuzzywuzzy (==0.18.0)
Requires-Dist: lxml (==4.9.2)
Requires-Dist: pydantic (==1.9.1)
Requires-Dist: pyperclip (==1.8.2)
Requires-Dist: PyYAML (==5.4.1)
Requires-Dist: requests (==2.28.0)
Requires-Dist: setuptools (==58.1.0)
Requires-Dist: spotipy (==2.21.0)
Requires-Dist: tqdm (==4.64.0)
Requires-Dist: youtube-dl (==2021.12.17)
Provides-Extra: levenshtein
Requires-Dist: python-Levenshtein (==0.12.2) ; extra == 'levenshtein'
